odoo/addons/account_reconcile_model_oca/README.rst
odoo/addons/account_reconcile_model_oca/__init__.py
odoo/addons/account_reconcile_model_oca/__manifest__.py
odoo/addons/account_reconcile_model_oca/i18n/account_reconcile_model_oca.pot
odoo/addons/account_reconcile_model_oca/i18n/fr.po
odoo/addons/account_reconcile_model_oca/i18n/it.po
odoo/addons/account_reconcile_model_oca/i18n/lv.po
odoo/addons/account_reconcile_model_oca/i18n/tr.po
odoo/addons/account_reconcile_model_oca/i18n/zh_CN.po
odoo/addons/account_reconcile_model_oca/models/__init__.py
odoo/addons/account_reconcile_model_oca/models/account_bank_statement_line.py
odoo/addons/account_reconcile_model_oca/models/account_reconcile_model.py
odoo/addons/account_reconcile_model_oca/readme/CONTRIBUTORS.md
odoo/addons/account_reconcile_model_oca/readme/CREDITS.md
odoo/addons/account_reconcile_model_oca/readme/DESCRIPTION.md
odoo/addons/account_reconcile_model_oca/static/description/icon.png
odoo/addons/account_reconcile_model_oca/static/description/index.html
odoo/addons/account_reconcile_model_oca/tests/__init__.py
odoo/addons/account_reconcile_model_oca/tests/common.py
odoo/addons/account_reconcile_model_oca/tests/test_reconciliation_match.py
odoo/addons/account_reconcile_model_oca/views/account_reconcile_model_views.xml
odoo_addon_account_reconcile_model_oca-18.0.1.1.0.1.dist-info/METADATA
odoo_addon_account_reconcile_model_oca-18.0.1.1.0.1.dist-info/WHEEL
odoo_addon_account_reconcile_model_oca-18.0.1.1.0.1.dist-info/top_level.txt
odoo_addon_account_reconcile_model_oca-18.0.1.1.0.1.dist-info/RECORD
