Metadata-Version: 2.1
Name: odoo-addon-account_reconcile_model_oca
Version: 18.0.1.1.0.1
Requires-Python: >=3.10
Requires-Dist: odoo==18.0.*
Summary: This includes the logic moved from Odoo Community to Odoo Enterprise
Home-page: https://github.com/OCA/account-reconcile
License: LGPL-3
Author: Dixmit,Odoo,Odoo Community Association (OCA)
Author-email: support@odoo-community.org
Classifier: Programming Language :: Python
Classifier: Framework :: Odoo
Classifier: Framework :: Odoo :: 18.0
Classifier: License :: OSI Approved :: GNU Lesser General Public License v3 (LGPLv3)
